ro_json/__init__.py
ro_json/_static_version.py
ro_json/_version.py
ro_json/comment.py
ro_json/decoders.py
ro_json/encoders.py
ro_json/nonp.py
ro_json/np.py
ro_json/np_utils.py
ro_json/utils.py
ro_json-1.0.4.dist-info/LICENSE.txt
ro_json-1.0.4.dist-info/METADATA
ro_json-1.0.4.dist-info/WHEEL
ro_json-1.0.4.dist-info/top_level.txt
ro_json-1.0.4.dist-info/RECORD
