Metadata-Version: 2.1
Name: ro-json
Version: 1.0.4
Summary: Extra features for Python's JSON: comments, order, numpy, pandas, datetimes, and many more! Simple but customizable.
Home-page: https://github.com/ramonaoptics/ro-json
Author: Clay Dugo
Author-email: clay@ramonaoptics.com
License: BSD-3-Clause
Project-URL: Source, https://github.com/ramonaoptics/ro_json
Project-URL: Tracker, https://github.com/ramonaoptics/ro_json/issues
Keywords: json,numpy,OrderedDict,comments,pandas,pytz,enum,encode,decode,serialize,deserialize,roundtrip
Classifier: Development Status :: 5 - Production/Stable
Classifier: Intended Audience :: Developers
Classifier: Natural Language :: English
Classifier: License :: OSI Approved :: BSD License
Classifier: Operating System :: OS Independent
Classifier: Programming Language :: Python :: 3 :: Only
Classifier: Programming Language :: Python :: 3.10
Classifier: Programming Language :: Python :: 3.11
Classifier: Programming Language :: Python :: 3.12
Classifier: Programming Language :: Python :: Implementation :: CPython
Classifier: Programming Language :: Python :: Implementation :: PyPy
Classifier: Topic :: Software Development :: Libraries :: Python Modules
Requires-Python: >=3.10
License-File: LICENSE.txt
